[
  {
    "name": "University of Cambridge",
    "url": "https://www.cam.ac.uk",
    "device": "mobile",
    "timestamp": "2025-10-31T06:30:59.509571",
    "lighthouse_version": "12.8.2",
    "test_type": "lab",
    "scores": {
      "performance": 36.0,
      "accessibility": 96.0,
      "best_practices": 100,
      "seo": 92.0
    },
    "metrics": {
      "first_contentful_paint": 3143.8795,
      "largest_contentful_paint": 12888.178500000002,
      "cumulative_layout_shift": 0,
      "total_blocking_time": 4291.500000000004,
      "speed_index": 5380.336170410625,
      "interactive": 13867.182750000004
    },
    "throttling_config": {
      "method": "simulate",
      "device": "mobile"
    }
  },
  {
    "name": "University of Cambridge",
    "url": "https://www.cam.ac.uk",
    "device": "desktop",
    "timestamp": "2025-10-31T06:31:00.996431",
    "lighthouse_version": "12.8.2",
    "test_type": "lab",
    "scores": {
      "performance": 75.0,
      "accessibility": 96.0,
      "best_practices": 100,
      "seo": 92.0
    },
    "metrics": {
      "first_contentful_paint": 742.3760000000001,
      "largest_contentful_paint": 2890.2164999999995,
      "cumulative_layout_shift": 0,
      "total_blocking_time": 880,
      "speed_index": 2054.8210254611076,
      "interactive": 3205.7754999999997
    },
    "throttling_config": {
      "method": "simulate",
      "device": "desktop"
    }
  },
  {
    "name": "Imperial College London",
    "url": "https://www.imperial.ac.uk",
    "device": "desktop",
    "timestamp": "2025-10-31T06:31:05.750304",
    "lighthouse_version": "12.8.2",
    "test_type": "lab",
    "scores": {
      "performance": 78.0,
      "accessibility": 97.0,
      "best_practices": 100,
      "seo": 92.0
    },
    "metrics": {
      "first_contentful_paint": 1040.9173999999998,
      "largest_contentful_paint": 1161.3157999999999,
      "cumulative_layout_shift": 0.04022122188773846,
      "total_blocking_time": 950.4999999999998,
      "speed_index": 1990.0459243402802,
      "interactive": 2863.6429799999996
    },
    "throttling_config": {
      "method": "simulate",
      "device": "desktop"
    }
  },
  {
    "name": "Imperial College London",
    "url": "https://www.imperial.ac.uk",
    "device": "mobile",
    "timestamp": "2025-10-31T06:31:06.301310",
    "lighthouse_version": "12.8.2",
    "test_type": "lab",
    "scores": {
      "performance": 51.0,
      "accessibility": 97.0,
      "best_practices": 100,
      "seo": 92.0
    },
    "metrics": {
      "first_contentful_paint": 2858.2913,
      "largest_contentful_paint": 3659.5373000000004,
      "cumulative_layout_shift": 0.02878069593949174,
      "total_blocking_time": 6729.0195,
      "speed_index": 5032.594089678649,
      "interactive": 12566.140965000002
    },
    "throttling_config": {
      "method": "simulate",
      "device": "mobile"
    }
  },
  {
    "name": "University of Oxford",
    "url": "https://www.ox.ac.uk",
    "device": "desktop",
    "timestamp": "2025-10-31T06:31:08.606114",
    "lighthouse_version": "12.8.2",
    "test_type": "lab",
    "scores": {
      "performance": 83.0,
      "accessibility": 95.0,
      "best_practices": 75.0,
      "seo": 100
    },
    "metrics": {
      "first_contentful_paint": 931.8939999999997,
      "largest_contentful_paint": 2057.051,
      "cumulative_layout_shift": 0.0034104548897212436,
      "total_blocking_time": 614.354000000001,
      "speed_index": 2347.7503905613576,
      "interactive": 2896.7547000000004
    },
    "throttling_config": {
      "method": "simulate",
      "device": "desktop"
    }
  },
  {
    "name": "University of Oxford",
    "url": "https://www.ox.ac.uk",
    "device": "mobile",
    "timestamp": "2025-10-31T06:31:10.587149",
    "lighthouse_version": "12.8.2",
    "test_type": "lab",
    "scores": {
      "performance": 35.0,
      "accessibility": 95.0,
      "best_practices": 75.0,
      "seo": 100
    },
    "metrics": {
      "first_contentful_paint": 3490.6320000000005,
      "largest_contentful_paint": 8181.345500000002,
      "cumulative_layout_shift": 0.01630374603774532,
      "total_blocking_time": 2600.568,
      "speed_index": 6144.0278076488885,
      "interactive": 12333.450099999998
    },
    "throttling_config": {
      "method": "simulate",
      "device": "mobile"
    }
  },
  {
    "name": "University College London",
    "url": "https://www.ucl.ac.uk",
    "device": "mobile",
    "timestamp": "2025-10-31T06:31:29.785883",
    "lighthouse_version": "12.8.2",
    "test_type": "lab",
    "scores": {
      "performance": 78.0,
      "accessibility": 96.0,
      "best_practices": 89.0,
      "seo": 100
    },
    "metrics": {
      "first_contentful_paint": 2584.9555,
      "largest_contentful_paint": 3131.259,
      "cumulative_layout_shift": 0,
      "total_blocking_time": 423.5519999999997,
      "speed_index": 3445.967224920445,
      "interactive": 3389.0208249999996
    },
    "throttling_config": {
      "method": "simulate",
      "device": "mobile"
    }
  },
  {
    "name": "University College London",
    "url": "https://www.ucl.ac.uk",
    "device": "desktop",
    "timestamp": "2025-10-31T06:31:30.308714",
    "lighthouse_version": "12.8.2",
    "test_type": "lab",
    "scores": {
      "performance": 100,
      "accessibility": 96.0,
      "best_practices": 89.0,
      "seo": 100
    },
    "metrics": {
      "first_contentful_paint": 944.9555,
      "largest_contentful_paint": 1092.8885,
      "cumulative_layout_shift": 0,
      "total_blocking_time": 19.999999999999886,
      "speed_index": 1940.6866719844593,
      "interactive": 1113.0658
    },
    "throttling_config": {
      "method": "simulate",
      "device": "desktop"
    }
  },
  {
    "name": "London School of Economics and Political Science",
    "url": "https://www.lse.ac.uk",
    "device": "desktop",
    "timestamp": "2025-10-31T06:31:34.484944",
    "lighthouse_version": "12.8.2",
    "test_type": "lab",
    "scores": {
      "performance": 66.0,
      "accessibility": 95.0,
      "best_practices": 54.0,
      "seo": 92.0
    },
    "metrics": {
      "first_contentful_paint": 1273.9365000000003,
      "largest_contentful_paint": 2451.9455000000003,
      "cumulative_layout_shift": 0.05610567390440982,
      "total_blocking_time": 3635.499999999999,
      "speed_index": 3410.1569267363634,
      "interactive": 8139.930249999999
    },
    "throttling_config": {
      "method": "simulate",
      "device": "desktop"
    }
  },
  {
    "name": "University of Edinburgh",
    "url": "https://www.ed.ac.uk",
    "device": "mobile",
    "timestamp": "2025-10-31T06:31:35.210625",
    "lighthouse_version": "12.8.2",
    "test_type": "lab",
    "scores": {
      "performance": 74.0,
      "accessibility": 98.0,
      "best_practices": 100,
      "seo": 100
    },
    "metrics": {
      "first_contentful_paint": 2126.886,
      "largest_contentful_paint": 3720.886,
      "cumulative_layout_shift": 0.07763703140028377,
      "total_blocking_time": 482,
      "speed_index": 2684.1501771166027,
      "interactive": 5145.586000000001
    },
    "throttling_config": {
      "method": "simulate",
      "device": "mobile"
    }
  },
  {
    "name": "University of Edinburgh",
    "url": "https://www.ed.ac.uk",
    "device": "desktop",
    "timestamp": "2025-10-31T06:31:37.027454",
    "lighthouse_version": "12.8.2",
    "test_type": "lab",
    "scores": {
      "performance": 99.0,
      "accessibility": 98.0,
      "best_practices": 100,
      "seo": 100
    },
    "metrics": {
      "first_contentful_paint": 470.9275,
      "largest_contentful_paint": 1149.4275,
      "cumulative_layout_shift": 0.07763703140028377,
      "total_blocking_time": 0,
      "speed_index": 1120.7249884980695,
      "interactive": 1153.5775
    },
    "throttling_config": {
      "method": "simulate",
      "device": "desktop"
    }
  },
  {
    "name": "King's College London",
    "url": "https://www.kcl.ac.uk",
    "device": "mobile",
    "timestamp": "2025-10-31T06:31:38.482826",
    "lighthouse_version": "12.8.2",
    "test_type": "lab",
    "scores": {
      "performance": 38.0,
      "accessibility": 94.0,
      "best_practices": 100,
      "seo": 100
    },
    "metrics": {
      "first_contentful_paint": 2940.0225,
      "largest_contentful_paint": 7318.51,
      "cumulative_layout_shift": 0,
      "total_blocking_time": 3912.481999999998,
      "speed_index": 4885.842621439234,
      "interactive": 11360.6643
    },
    "throttling_config": {
      "method": "simulate",
      "device": "mobile"
    }
  },
  {
    "name": "King's College London",
    "url": "https://www.kcl.ac.uk",
    "device": "desktop",
    "timestamp": "2025-10-31T06:31:40.821111",
    "lighthouse_version": "12.8.2",
    "test_type": "lab",
    "scores": {
      "performance": 83.0,
      "accessibility": 94.0,
      "best_practices": 100,
      "seo": 100
    },
    "metrics": {
      "first_contentful_paint": 1078.4085,
      "largest_contentful_paint": 1826.0094999999997,
      "cumulative_layout_shift": 0,
      "total_blocking_time": 645.5,
      "speed_index": 1810.225210303522,
      "interactive": 2591.1915
    },
    "throttling_config": {
      "method": "simulate",
      "device": "desktop"
    }
  },
  {
    "name": "University of Glasgow",
    "url": "https://www.gla.ac.uk",
    "device": "mobile",
    "timestamp": "2025-10-31T06:32:15.396489",
    "lighthouse_version": "12.8.2",
    "test_type": "lab",
    "scores": {
      "performance": 5.0,
      "accessibility": 100,
      "best_practices": 100,
      "seo": 100
    },
    "metrics": {
      "first_contentful_paint": 5972.336999999999,
      "largest_contentful_paint": 10001.233,
      "cumulative_layout_shift": 0.7788814307116988,
      "total_blocking_time": 4538.1335,
      "speed_index": 7164.060200406007,
      "interactive": 12900.722999999998
    },
    "throttling_config": {
      "method": "simulate",
      "device": "mobile"
    }
  },
  {
    "name": "University of Glasgow",
    "url": "https://www.gla.ac.uk",
    "device": "desktop",
    "timestamp": "2025-10-31T06:32:15.777479",
    "lighthouse_version": "12.8.2",
    "test_type": "lab",
    "scores": {
      "performance": 57.99999999999999,
      "accessibility": 100,
      "best_practices": 100,
      "seo": 100
    },
    "metrics": {
      "first_contentful_paint": 1784.534,
      "largest_contentful_paint": 2507.965,
      "cumulative_layout_shift": 0.7788814307116988,
      "total_blocking_time": 562.925999999999,
      "speed_index": 2386.553452192294,
      "interactive": 2820.7099
    },
    "throttling_config": {
      "method": "simulate",
      "device": "desktop"
    }
  },
  {
    "name": "University of Southampton",
    "url": "https://www.southampton.ac.uk",
    "device": "mobile",
    "timestamp": "2025-10-31T06:32:17.834865",
    "lighthouse_version": "12.8.2",
    "test_type": "lab",
    "scores": {
      "performance": 39.0,
      "accessibility": 85.0,
      "best_practices": 75.0,
      "seo": 69.0
    },
    "metrics": {
      "first_contentful_paint": 3279.1890000000003,
      "largest_contentful_paint": 6149.776000000002,
      "cumulative_layout_shift": 0,
      "total_blocking_time": 2573.49625,
      "speed_index": 5119.461645546269,
      "interactive": 9730.714625000002
    },
    "throttling_config": {
      "method": "simulate",
      "device": "mobile"
    }
  },
  {
    "name": "London School of Economics and Political Science",
    "url": "https://www.lse.ac.uk",
    "device": "mobile",
    "timestamp": "2025-10-31T06:32:19.696342",
    "lighthouse_version": "12.8.2",
    "test_type": "lab",
    "scores": {
      "performance": 32.0,
      "accessibility": 95.0,
      "best_practices": 54.0,
      "seo": 92.0
    },
    "metrics": {
      "first_contentful_paint": 3854.2239999999997,
      "largest_contentful_paint": 6076.0866,
      "cumulative_layout_shift": 0.05598903929995615,
      "total_blocking_time": 25664.999999999996,
      "speed_index": 7999.105465021762,
      "interactive": 36409.9647
    },
    "throttling_config": {
      "method": "simulate",
      "device": "mobile"
    }
  },
  {
    "name": "University of Birmingham",
    "url": "https://www.birmingham.ac.uk",
    "device": "mobile",
    "timestamp": "2025-10-31T06:32:38.830051",
    "lighthouse_version": "12.8.2",
    "test_type": "lab",
    "scores": {
      "performance": 35.0,
      "accessibility": 99.0,
      "best_practices": 96.0,
      "seo": 100
    },
    "metrics": {
      "first_contentful_paint": 3281.948016052246,
      "largest_contentful_paint": 13098.665,
      "cumulative_layout_shift": 6.708245653719757e-06,
      "total_blocking_time": 2323.999999999999,
      "speed_index": 6239.417484758007,
      "interactive": 13140.806750000002
    },
    "throttling_config": {
      "method": "simulate",
      "device": "mobile"
    }
  },
  {
    "name": "University of Birmingham",
    "url": "https://www.birmingham.ac.uk",
    "device": "desktop",
    "timestamp": "2025-10-31T06:32:40.980386",
    "lighthouse_version": "12.8.2",
    "test_type": "lab",
    "scores": {
      "performance": 90.0,
      "accessibility": 99.0,
      "best_practices": 96.0,
      "seo": 100
    },
    "metrics": {
      "first_contentful_paint": 2576.514,
      "largest_contentful_paint": 3008.5950000000003,
      "cumulative_layout_shift": 0,
      "total_blocking_time": 2,
      "speed_index": 2925.6368693188324,
      "interactive": 3075.7446
    },
    "throttling_config": {
      "method": "simulate",
      "device": "desktop"
    }
  },
  {
    "name": "University of Leeds",
    "url": "https://www.leeds.ac.uk",
    "device": "mobile",
    "timestamp": "2025-10-31T06:32:41.036911",
    "lighthouse_version": "12.8.2",
    "test_type": "lab",
    "scores": {
      "performance": 41.0,
      "accessibility": 100,
      "best_practices": 96.0,
      "seo": 100
    },
    "metrics": {
      "first_contentful_paint": 3588.6531999999997,
      "largest_contentful_paint": 6250.566000000001,
      "cumulative_layout_shift": 0.4359431956257594,
      "total_blocking_time": 369.00000000000045,
      "speed_index": 3588.6531999999997,
      "interactive": 6280.650000000001
    },
    "throttling_config": {
      "method": "simulate",
      "device": "mobile"
    }
  },
  {
    "name": "University of Southampton",
    "url": "https://www.southampton.ac.uk",
    "device": "desktop",
    "timestamp": "2025-10-31T06:32:46.403762",
    "lighthouse_version": "12.8.2",
    "test_type": "lab",
    "scores": {
      "performance": 90.0,
      "accessibility": 85.0,
      "best_practices": 75.0,
      "seo": 69.0
    },
    "metrics": {
      "first_contentful_paint": 1700.8549999999996,
      "largest_contentful_paint": 2567.5012500000003,
      "cumulative_layout_shift": 0,
      "total_blocking_time": 284.5,
      "speed_index": 2666.935580522141,
      "interactive": 2656.7397250000004
    },
    "throttling_config": {
      "method": "simulate",
      "device": "desktop"
    }
  },
  {
    "name": "University of Leeds",
    "url": "https://www.leeds.ac.uk",
    "device": "desktop",
    "timestamp": "2025-10-31T06:33:13.721100",
    "lighthouse_version": "12.8.2",
    "test_type": "lab",
    "scores": {
      "performance": 77.0,
      "accessibility": 100,
      "best_practices": 96.0,
      "seo": 100
    },
    "metrics": {
      "first_contentful_paint": 1750.0448599999997,
      "largest_contentful_paint": 2347.257,
      "cumulative_layout_shift": 0.4359431956257594,
      "total_blocking_time": 28.110979999999927,
      "speed_index": 1750.0448599999997,
      "interactive": 2347.2570000000005
    },
    "throttling_config": {
      "method": "simulate",
      "device": "desktop"
    }
  },
  {
    "name": "University of Sheffield",
    "url": "https://www.sheffield.ac.uk",
    "device": "desktop",
    "timestamp": "2025-10-31T06:33:27.351261",
    "lighthouse_version": "12.8.2",
    "test_type": "lab",
    "scores": {
      "performance": 93.0,
      "accessibility": 99.0,
      "best_practices": 96.0,
      "seo": 100
    },
    "metrics": {
      "first_contentful_paint": 1603.4025,
      "largest_contentful_paint": 2060.5535,
      "cumulative_layout_shift": 0.025874898571827402,
      "total_blocking_time": 276.4999999999998,
      "speed_index": 2053.0508724023894,
      "interactive": 2589.1443500000005
    },
    "throttling_config": {
      "method": "simulate",
      "device": "desktop"
    }
  },
  {
    "name": "University of Sheffield",
    "url": "https://www.sheffield.ac.uk",
    "device": "mobile",
    "timestamp": "2025-10-31T06:33:28.276817",
    "lighthouse_version": "12.8.2",
    "test_type": "lab",
    "scores": {
      "performance": 38.0,
      "accessibility": 99.0,
      "best_practices": 96.0,
      "seo": 100
    },
    "metrics": {
      "first_contentful_paint": 3943.11365,
      "largest_contentful_paint": 6482.20981,
      "cumulative_layout_shift": 0.025484143262498225,
      "total_blocking_time": 2147.645429999998,
      "speed_index": 5087.02622973474,
      "interactive": 9104.645267
    },
    "throttling_config": {
      "method": "simulate",
      "device": "mobile"
    }
  },
  {
    "name": "University of Warwick",
    "url": "https://www.warwick.ac.uk",
    "device": "mobile",
    "timestamp": "2025-10-31T06:33:31.860532",
    "lighthouse_version": "12.8.2",
    "test_type": "lab",
    "scores": {
      "performance": 26.0,
      "accessibility": 100,
      "best_practices": 79.0,
      "seo": 92.0
    },
    "metrics": {
      "first_contentful_paint": 6359.689,
      "largest_contentful_paint": 16562.950206237794,
      "cumulative_layout_shift": 0.00019083107801421654,
      "total_blocking_time": 4601,
      "speed_index": 9998.549378816086,
      "interactive": 19643.37385
    },
    "throttling_config": {
      "method": "simulate",
      "device": "mobile"
    }
  },
  {
    "name": "University of Warwick",
    "url": "https://www.warwick.ac.uk",
    "device": "desktop",
    "timestamp": "2025-10-31T06:33:33.519528",
    "lighthouse_version": "12.8.2",
    "test_type": "lab",
    "scores": {
      "performance": 69.0,
      "accessibility": 100,
      "best_practices": 79.0,
      "seo": 92.0
    },
    "metrics": {
      "first_contentful_paint": 1849.9260000000002,
      "largest_contentful_paint": 3366.688,
      "cumulative_layout_shift": 8.488611631378402e-06,
      "total_blocking_time": 985.0000000000005,
      "speed_index": 3000.3719805592486,
      "interactive": 4384.851450000001
    },
    "throttling_config": {
      "method": "simulate",
      "device": "desktop"
    }
  },
  {
    "name": "University of Nottingham",
    "url": "https://www.nottingham.ac.uk",
    "device": "mobile",
    "timestamp": "2025-10-31T06:33:40.716232",
    "lighthouse_version": "12.8.2",
    "test_type": "lab",
    "scores": {
      "performance": 26.0,
      "accessibility": 92.0,
      "best_practices": 100,
      "seo": 75.0
    },
    "metrics": {
      "first_contentful_paint": 11069.401000000002,
      "largest_contentful_paint": 14824.379800000002,
      "cumulative_layout_shift": 0.01778456259808749,
      "total_blocking_time": 9116.871999999996,
      "speed_index": 11069.401000000002,
      "interactive": 21043.400999999998
    },
    "throttling_config": {
      "method": "simulate",
      "device": "mobile"
    }
  },
  {
    "name": "University of Manchester",
    "url": "https://www.manchester.ac.uk",
    "device": "mobile",
    "timestamp": "2025-10-31T06:33:40.951190",
    "lighthouse_version": "12.8.2",
    "test_type": "lab",
    "scores": {
      "performance": 43.0,
      "accessibility": 100,
      "best_practices": 75.0,
      "seo": 92.0
    },
    "metrics": {
      "first_contentful_paint": 2574.7700000000004,
      "largest_contentful_paint": 6207.764499999999,
      "cumulative_layout_shift": 0.001158986504199455,
      "total_blocking_time": 19882.640999999996,
      "speed_index": 3272.2055788091297,
      "interactive": 34627.36439999999
    },
    "throttling_config": {
      "method": "simulate",
      "device": "mobile"
    }
  },
  {
    "name": "University of Manchester",
    "url": "https://www.manchester.ac.uk",
    "device": "desktop",
    "timestamp": "2025-10-31T06:33:41.881630",
    "lighthouse_version": "12.8.2",
    "test_type": "lab",
    "scores": {
      "performance": 64.0,
      "accessibility": 100,
      "best_practices": 75.0,
      "seo": 92.0
    },
    "metrics": {
      "first_contentful_paint": 2212.2605,
      "largest_contentful_paint": 2772.2605000000003,
      "cumulative_layout_shift": 0.001158986504199455,
      "total_blocking_time": 3738.0000000000014,
      "speed_index": 2548.6278588333316,
      "interactive": 8091.4004
    },
    "throttling_config": {
      "method": "simulate",
      "device": "desktop"
    }
  },
  {
    "name": "University of Nottingham",
    "url": "https://www.nottingham.ac.uk",
    "device": "desktop",
    "timestamp": "2025-10-31T06:33:56.312601",
    "lighthouse_version": "12.8.2",
    "test_type": "lab",
    "scores": {
      "performance": 64.0,
      "accessibility": 92.0,
      "best_practices": 100,
      "seo": 75.0
    },
    "metrics": {
      "first_contentful_paint": 2465.3320000000003,
      "largest_contentful_paint": 3241.86292,
      "cumulative_layout_shift": 0.015231888786690073,
      "total_blocking_time": 1336.4359999999997,
      "speed_index": 3165.702029743708,
      "interactive": 4485.3002
    },
    "throttling_config": {
      "method": "simulate",
      "device": "desktop"
    }
  },
  {
    "name": "Lancaster University",
    "url": "https://www.lancaster.ac.uk",
    "device": "mobile",
    "timestamp": "2025-10-31T06:34:02.527619",
    "lighthouse_version": "12.8.2",
    "test_type": "lab",
    "scores": {
      "performance": 53.0,
      "accessibility": 100,
      "best_practices": 100,
      "seo": 100
    },
    "metrics": {
      "first_contentful_paint": 2949.317,
      "largest_contentful_paint": 4951.956999999999,
      "cumulative_layout_shift": 0,
      "total_blocking_time": 1184.499999999999,
      "speed_index": 3020.7309552880924,
      "interactive": 6429.217575
    },
    "throttling_config": {
      "method": "simulate",
      "device": "mobile"
    }
  },
  {
    "name": "Lancaster University",
    "url": "https://www.lancaster.ac.uk",
    "device": "desktop",
    "timestamp": "2025-10-31T06:34:03.678893",
    "lighthouse_version": "12.8.2",
    "test_type": "lab",
    "scores": {
      "performance": 100,
      "accessibility": 100,
      "best_practices": 100,
      "seo": 100
    },
    "metrics": {
      "first_contentful_paint": 1112.8839999999998,
      "largest_contentful_paint": 1651.5499999999995,
      "cumulative_layout_shift": 0.0009271139506038332,
      "total_blocking_time": 25.499999999999773,
      "speed_index": 1355.32175420784,
      "interactive": 1835.4496499999993
    },
    "throttling_config": {
      "method": "simulate",
      "device": "desktop"
    }
  },
  {
    "name": "University of Exeter",
    "url": "https://www.exeter.ac.uk",
    "device": "desktop",
    "timestamp": "2025-10-31T06:34:06.692022",
    "lighthouse_version": "12.8.2",
    "test_type": "lab",
    "scores": {
      "performance": 89.0,
      "accessibility": 95.0,
      "best_practices": 61.0,
      "seo": 100
    },
    "metrics": {
      "first_contentful_paint": 786.2194999999999,
      "largest_contentful_paint": 1111.1045,
      "cumulative_layout_shift": 0,
      "total_blocking_time": 437,
      "speed_index": 1372.497611882135,
      "interactive": 2793.54955
    },
    "throttling_config": {
      "method": "simulate",
      "device": "desktop"
    }
  },
  {
    "name": "University of Exeter",
    "url": "https://www.exeter.ac.uk",
    "device": "mobile",
    "timestamp": "2025-10-31T06:34:07.227329",
    "lighthouse_version": "12.8.2",
    "test_type": "lab",
    "scores": {
      "performance": 35.0,
      "accessibility": 95.0,
      "best_practices": 61.0,
      "seo": 100
    },
    "metrics": {
      "first_contentful_paint": 2759.357,
      "largest_contentful_paint": 11552.357000000002,
      "cumulative_layout_shift": 0,
      "total_blocking_time": 3813.5440000000017,
      "speed_index": 6533.885506761127,
      "interactive": 11889.980100000002
    },
    "throttling_config": {
      "method": "simulate",
      "device": "mobile"
    }
  },
  {
    "name": "University of Bath",
    "url": "https://www.bath.ac.uk",
    "device": "mobile",
    "timestamp": "2025-10-31T06:34:25.897506",
    "lighthouse_version": "12.8.2",
    "test_type": "lab",
    "scores": {
      "performance": 44.0,
      "accessibility": 100,
      "best_practices": 71.0,
      "seo": 100
    },
    "metrics": {
      "first_contentful_paint": 2074.129,
      "largest_contentful_paint": 8064.052,
      "cumulative_layout_shift": 0.15377756701501574,
      "total_blocking_time": 1038,
      "speed_index": 3820.219223825006,
      "interactive": 8915.361650000003
    },
    "throttling_config": {
      "method": "simulate",
      "device": "mobile"
    }
  },
  {
    "name": "University of Bath",
    "url": "https://www.bath.ac.uk",
    "device": "desktop",
    "timestamp": "2025-10-31T06:34:26.031770",
    "lighthouse_version": "12.8.2",
    "test_type": "lab",
    "scores": {
      "performance": 91.0,
      "accessibility": 100,
      "best_practices": 71.0,
      "seo": 100
    },
    "metrics": {
      "first_contentful_paint": 887.5369999999999,
      "largest_contentful_paint": 2048.9289999999996,
      "cumulative_layout_shift": 0.1670300497566204,
      "total_blocking_time": 86.5,
      "speed_index": 1400.2001701306674,
      "interactive": 2313.36895
    },
    "throttling_config": {
      "method": "simulate",
      "device": "desktop"
    }
  },
  {
    "name": "Cardiff University",
    "url": "https://www.cardiff.ac.uk",
    "device": "mobile",
    "timestamp": "2025-10-31T06:34:28.130523",
    "lighthouse_version": "12.8.2",
    "test_type": "lab",
    "scores": {
      "performance": 49.0,
      "accessibility": 93.0,
      "best_practices": 100,
      "seo": 100
    },
    "metrics": {
      "first_contentful_paint": 3035.5209999999997,
      "largest_contentful_paint": 6154.761499999999,
      "cumulative_layout_shift": 0.044779775820463955,
      "total_blocking_time": 1098,
      "speed_index": 3035.5209999999997,
      "interactive": 9036.283150000003
    },
    "throttling_config": {
      "method": "simulate",
      "device": "mobile"
    }
  },
  {
    "name": "Cardiff University",
    "url": "https://www.cardiff.ac.uk",
    "device": "desktop",
    "timestamp": "2025-10-31T06:34:28.264443",
    "lighthouse_version": "12.8.2",
    "test_type": "lab",
    "scores": {
      "performance": 98.0,
      "accessibility": 93.0,
      "best_practices": 100,
      "seo": 100
    },
    "metrics": {
      "first_contentful_paint": 1094.5992499999998,
      "largest_contentful_paint": 2233.2934999999998,
      "cumulative_layout_shift": 0.044788027643476294,
      "total_blocking_time": 42.500000000000114,
      "speed_index": 1555.6219568293145,
      "interactive": 2249.3843
    },
    "throttling_config": {
      "method": "simulate",
      "device": "desktop"
    }
  },
  {
    "name": "University of Liverpool",
    "url": "https://www.liverpool.ac.uk",
    "device": "desktop",
    "timestamp": "2025-10-31T06:34:59.121983",
    "lighthouse_version": "12.8.2",
    "test_type": "lab",
    "scores": {
      "performance": 96.0,
      "accessibility": 95.0,
      "best_practices": 79.0,
      "seo": 100
    },
    "metrics": {
      "first_contentful_paint": 1484.442,
      "largest_contentful_paint": 2181.4665,
      "cumulative_layout_shift": 0.08929354076428161,
      "total_blocking_time": 39.5,
      "speed_index": 2062.0928073762093,
      "interactive": 3142.5355
    },
    "throttling_config": {
      "method": "simulate",
      "device": "desktop"
    }
  },
  {
    "name": "University of Liverpool",
    "url": "https://www.liverpool.ac.uk",
    "device": "mobile",
    "timestamp": "2025-10-31T06:34:59.477904",
    "lighthouse_version": "12.8.2",
    "test_type": "lab",
    "scores": {
      "performance": 40.0,
      "accessibility": 95.0,
      "best_practices": 79.0,
      "seo": 100
    },
    "metrics": {
      "first_contentful_paint": 3972.8777,
      "largest_contentful_paint": 10636.21565,
      "cumulative_layout_shift": 0.08929354076428161,
      "total_blocking_time": 960.4999999999991,
      "speed_index": 5383.453203771378,
      "interactive": 15233.881
    },
    "throttling_config": {
      "method": "simulate",
      "device": "mobile"
    }
  },
  {
    "name": "University of St Andrews",
    "url": "https://www.st-andrews.ac.uk",
    "device": "desktop",
    "timestamp": "2025-10-31T06:35:01.357331",
    "lighthouse_version": "12.8.2",
    "test_type": "lab",
    "scores": {
      "performance": 94.0,
      "accessibility": 98.0,
      "best_practices": 79.0,
      "seo": 83.0
    },
    "metrics": {
      "first_contentful_paint": 1922.3515,
      "largest_contentful_paint": 2242.3514999999998,
      "cumulative_layout_shift": 0,
      "total_blocking_time": 217,
      "speed_index": 1922.3515,
      "interactive": 4114.021275
    },
    "throttling_config": {
      "method": "simulate",
      "device": "desktop"
    }
  },
  {
    "name": "University of St Andrews",
    "url": "https://www.st-andrews.ac.uk",
    "device": "mobile",
    "timestamp": "2025-10-31T06:35:01.503329",
    "lighthouse_version": "12.8.2",
    "test_type": "lab",
    "scores": {
      "performance": 27.0,
      "accessibility": 98.0,
      "best_practices": 79.0,
      "seo": 83.0
    },
    "metrics": {
      "first_contentful_paint": 8583.207999999999,
      "largest_contentful_paint": 9858.207999999999,
      "cumulative_layout_shift": 0,
      "total_blocking_time": 3458.035249999997,
      "speed_index": 8583.207999999999,
      "interactive": 21104.972650000003
    },
    "throttling_config": {
      "method": "simulate",
      "device": "mobile"
    }
  },
  {
    "name": "Queen Mary University of London",
    "url": "https://www.qmul.ac.uk",
    "device": "mobile",
    "timestamp": "2025-10-31T06:35:08.518994",
    "lighthouse_version": "12.8.2",
    "test_type": "lab",
    "scores": {
      "performance": 28.000000000000004,
      "accessibility": 95.0,
      "best_practices": 75.0,
      "seo": 92.0
    },
    "metrics": {
      "first_contentful_paint": 4639.685500000001,
      "largest_contentful_paint": 19372.402999999995,
      "cumulative_layout_shift": 0,
      "total_blocking_time": 8846.8255,
      "speed_index": 9200.57273139875,
      "interactive": 23392.361699999994
    },
    "throttling_config": {
      "method": "simulate",
      "device": "mobile"
    }
  },
  {
    "name": "Queen Mary University of London",
    "url": "https://www.qmul.ac.uk",
    "device": "desktop",
    "timestamp": "2025-10-31T06:35:12.941999",
    "lighthouse_version": "12.8.2",
    "test_type": "lab",
    "scores": {
      "performance": 65.0,
      "accessibility": 95.0,
      "best_practices": 75.0,
      "seo": 92.0
    },
    "metrics": {
      "first_contentful_paint": 1207.076,
      "largest_contentful_paint": 3455.8130000000006,
      "cumulative_layout_shift": 0,
      "total_blocking_time": 1537.7599999999984,
      "speed_index": 2691.1190515113276,
      "interactive": 5116.9321
    },
    "throttling_config": {
      "method": "simulate",
      "device": "desktop"
    }
  },
  {
    "name": "University of York",
    "url": "https://www.york.ac.uk",
    "device": "mobile",
    "timestamp": "2025-10-31T06:35:26.537431",
    "lighthouse_version": "12.8.2",
    "test_type": "lab",
    "scores": {
      "performance": 54.0,
      "accessibility": 95.0,
      "best_practices": 79.0,
      "seo": 92.0
    },
    "metrics": {
      "first_contentful_paint": 1204.078,
      "largest_contentful_paint": 2625.1099999999997,
      "cumulative_layout_shift": 0.1250979808237022,
      "total_blocking_time": 6138.999999999997,
      "speed_index": 8819.215305439902,
      "interactive": 17607.2234
    },
    "throttling_config": {
      "method": "simulate",
      "device": "mobile"
    }
  },
  {
    "name": "University of Sussex",
    "url": "https://www.sussex.ac.uk",
    "device": "mobile",
    "timestamp": "2025-10-31T06:35:27.587721",
    "lighthouse_version": "12.8.2",
    "test_type": "lab",
    "scores": {
      "performance": 69.0,
      "accessibility": 97.0,
      "best_practices": 100,
      "seo": 100
    },
    "metrics": {
      "first_contentful_paint": 1215.4139999999998,
      "largest_contentful_paint": 4515.414,
      "cumulative_layout_shift": 0,
      "total_blocking_time": 577,
      "speed_index": 3193.7881971667553,
      "interactive": 4560.414
    },
    "throttling_config": {
      "method": "simulate",
      "device": "mobile"
    }
  },
  {
    "name": "University of Sussex",
    "url": "https://www.sussex.ac.uk",
    "device": "desktop",
    "timestamp": "2025-10-31T06:35:29.742596",
    "lighthouse_version": "12.8.2",
    "test_type": "lab",
    "scores": {
      "performance": 100,
      "accessibility": 97.0,
      "best_practices": 100,
      "seo": 100
    },
    "metrics": {
      "first_contentful_paint": 335.1740000000001,
      "largest_contentful_paint": 895.1740000000001,
      "cumulative_layout_shift": 0,
      "total_blocking_time": 0,
      "speed_index": 1118.7577122242772,
      "interactive": 903.1740000000002
    },
    "throttling_config": {
      "method": "simulate",
      "device": "desktop"
    }
  },
  {
    "name": "University of York",
    "url": "https://www.york.ac.uk",
    "device": "desktop",
    "timestamp": "2025-10-31T06:35:42.013783",
    "lighthouse_version": "12.8.2",
    "test_type": "lab",
    "scores": {
      "performance": 85.0,
      "accessibility": 95.0,
      "best_practices": 79.0,
      "seo": 92.0
    },
    "metrics": {
      "first_contentful_paint": 508.3684999999999,
      "largest_contentful_paint": 2339.65720425415,
      "cumulative_layout_shift": 0.12530094831229355,
      "total_blocking_time": 367.0000000000002,
      "speed_index": 1069.3769217500057,
      "interactive": 3426.4767
    },
    "throttling_config": {
      "method": "simulate",
      "device": "desktop"
    }
  },
  {
    "name": "University of Surrey",
    "url": "https://www.surrey.ac.uk",
    "device": "mobile",
    "timestamp": "2025-10-31T06:35:47.570927",
    "lighthouse_version": "12.8.2",
    "test_type": "lab",
    "scores": {
      "performance": 74.0,
      "accessibility": 100,
      "best_practices": 100,
      "seo": 100
    },
    "metrics": {
      "first_contentful_paint": 2277.5225,
      "largest_contentful_paint": 3591.7675,
      "cumulative_layout_shift": 0.0022677310435549043,
      "total_blocking_time": 523.9265,
      "speed_index": 3257.657974228001,
      "interactive": 6369.87535
    },
    "throttling_config": {
      "method": "simulate",
      "device": "mobile"
    }
  },
  {
    "name": "University of Surrey",
    "url": "https://www.surrey.ac.uk",
    "device": "desktop",
    "timestamp": "2025-10-31T06:35:48.926415",
    "lighthouse_version": "12.8.2",
    "test_type": "lab",
    "scores": {
      "performance": 100,
      "accessibility": 100,
      "best_practices": 100,
      "seo": 100
    },
    "metrics": {
      "first_contentful_paint": 957.129,
      "largest_contentful_paint": 1767.2570000000003,
      "cumulative_layout_shift": 0.0022677310435549043,
      "total_blocking_time": 48.5,
      "speed_index": 2033.6592243795217,
      "interactive": 1877.0553000000004
    },
    "throttling_config": {
      "method": "simulate",
      "device": "desktop"
    }
  },
  {
    "name": "University of Newcastle",
    "url": "https://www.ncl.ac.uk",
    "device": "mobile",
    "timestamp": "2025-10-31T06:36:16.101501",
    "lighthouse_version": "12.8.2",
    "test_type": "lab",
    "scores": {
      "performance": 36.0,
      "accessibility": 92.0,
      "best_practices": 100,
      "seo": 100
    },
    "metrics": {
      "first_contentful_paint": 3001.48575,
      "largest_contentful_paint": 16510.344,
      "cumulative_layout_shift": 0,
      "total_blocking_time": 8584.318000000001,
      "speed_index": 5388.495931752647,
      "interactive": 23162.0772
    },
    "throttling_config": {
      "method": "simulate",
      "device": "mobile"
    }
  },
  {
    "name": "University of Newcastle",
    "url": "https://www.ncl.ac.uk",
    "device": "desktop",
    "timestamp": "2025-10-31T06:36:17.724438",
    "lighthouse_version": "12.8.2",
    "test_type": "lab",
    "scores": {
      "performance": 65.0,
      "accessibility": 92.0,
      "best_practices": 100,
      "seo": 100
    },
    "metrics": {
      "first_contentful_paint": 1161.45525,
      "largest_contentful_paint": 3340.3734999999997,
      "cumulative_layout_shift": 0,
      "total_blocking_time": 1661.9754999999998,
      "speed_index": 2148.500715382044,
      "interactive": 5344.074450000001
    },
    "throttling_config": {
      "method": "simulate",
      "device": "desktop"
    }
  },
  {
    "name": "University of Aberdeen",
    "url": "https://www.abdn.ac.uk",
    "device": "mobile",
    "timestamp": "2025-10-31T06:36:20.014183",
    "lighthouse_version": "12.8.2",
    "test_type": "lab",
    "scores": {
      "performance": 30.0,
      "accessibility": 97.0,
      "best_practices": 75.0,
      "seo": 100
    },
    "metrics": {
      "first_contentful_paint": 3949.5983999999994,
      "largest_contentful_paint": 11974.283500000001,
      "cumulative_layout_shift": 0.03649355871528897,
      "total_blocking_time": 1854.0000000000018,
      "speed_index": 14768.435487827544,
      "interactive": 11999.432950000002
    },
    "throttling_config": {
      "method": "simulate",
      "device": "mobile"
    }
  },
  {
    "name": "University of Aberdeen",
    "url": "https://www.abdn.ac.uk",
    "device": "desktop",
    "timestamp": "2025-10-31T06:36:29.198496",
    "lighthouse_version": "12.8.2",
    "test_type": "lab",
    "scores": {
      "performance": 86.0,
      "accessibility": 97.0,
      "best_practices": 75.0,
      "seo": 100
    },
    "metrics": {
      "first_contentful_paint": 1241.2135999999998,
      "largest_contentful_paint": 2706.001,
      "cumulative_layout_shift": 0.08438061398995746,
      "total_blocking_time": 222,
      "speed_index": 5464.305959691468,
      "interactive": 2712.108400000001
    },
    "throttling_config": {
      "method": "simulate",
      "device": "desktop"
    }
  },
  {
    "name": "University of Dundee",
    "url": "https://www.dundee.ac.uk",
    "device": "desktop",
    "timestamp": "2025-10-31T06:36:29.781368",
    "lighthouse_version": "12.8.2",
    "test_type": "lab",
    "scores": {
      "performance": 98.0,
      "accessibility": 91.0,
      "best_practices": 100,
      "seo": 92.0
    },
    "metrics": {
      "first_contentful_paint": 886.8079868927002,
      "largest_contentful_paint": 1884.02325,
      "cumulative_layout_shift": 2.636668428918977e-05,
      "total_blocking_time": 145.9999999999999,
      "speed_index": 2126.277819912892,
      "interactive": 2142.738725
    },
    "throttling_config": {
      "method": "simulate",
      "device": "desktop"
    }
  },
  {
    "name": "University of Dundee",
    "url": "https://www.dundee.ac.uk",
    "device": "mobile",
    "timestamp": "2025-10-31T06:36:30.924748",
    "lighthouse_version": "12.8.2",
    "test_type": "lab",
    "scores": {
      "performance": 36.0,
      "accessibility": 91.0,
      "best_practices": 100,
      "seo": 92.0
    },
    "metrics": {
      "first_contentful_paint": 2935.5914868927002,
      "largest_contentful_paint": 8543.594,
      "cumulative_layout_shift": 2.905383477507818e-05,
      "total_blocking_time": 3112.499999999999,
      "speed_index": 5910.31550793868,
      "interactive": 10130.871475
    },
    "throttling_config": {
      "method": "simulate",
      "device": "mobile"
    }
  },
  {
    "name": "Heriot-Watt University",
    "url": "https://www.hw.ac.uk",
    "device": "desktop",
    "timestamp": "2025-10-31T06:36:52.287606",
    "lighthouse_version": "12.8.2",
    "test_type": "lab",
    "scores": {
      "performance": 95.0,
      "accessibility": 95.0,
      "best_practices": 96.0,
      "seo": 92.0
    },
    "metrics": {
      "first_contentful_paint": 1440.782,
      "largest_contentful_paint": 2317.80525,
      "cumulative_layout_shift": 0.03967643493782195,
      "total_blocking_time": 197.5,
      "speed_index": 1737.012187494005,
      "interactive": 2669.3332500000006
    },
    "throttling_config": {
      "method": "simulate",
      "device": "desktop"
    }
  },
  {
    "name": "Heriot-Watt University",
    "url": "https://www.hw.ac.uk",
    "device": "mobile",
    "timestamp": "2025-10-31T06:36:52.344055",
    "lighthouse_version": "12.8.2",
    "test_type": "lab",
    "scores": {
      "performance": 36.0,
      "accessibility": 95.0,
      "best_practices": 96.0,
      "seo": 92.0
    },
    "metrics": {
      "first_contentful_paint": 3109.0505000000003,
      "largest_contentful_paint": 9653.609690000001,
      "cumulative_layout_shift": 0.048800480390658416,
      "total_blocking_time": 3295.6655,
      "speed_index": 4965.541190245622,
      "interactive": 18171.383300000005
    },
    "throttling_config": {
      "method": "simulate",
      "device": "mobile"
    }
  },
  {
    "name": "University of Strathclyde",
    "url": "https://www.strath.ac.uk",
    "device": "mobile",
    "timestamp": "2025-10-31T06:36:54.068069",
    "lighthouse_version": "12.8.2",
    "test_type": "lab",
    "scores": {
      "performance": 45.0,
      "accessibility": 100,
      "best_practices": 75.0,
      "seo": 100
    },
    "metrics": {
      "first_contentful_paint": 3252.117,
      "largest_contentful_paint": 10631.946,
      "cumulative_layout_shift": 0.01976696968275746,
      "total_blocking_time": 887.5564999999997,
      "speed_index": 4914.61960605171,
      "interactive": 12686.903850000002
    },
    "throttling_config": {
      "method": "simulate",
      "device": "mobile"
    }
  },
  {
    "name": "University of Strathclyde",
    "url": "https://www.strath.ac.uk",
    "device": "desktop",
    "timestamp": "2025-10-31T06:37:01.205419",
    "lighthouse_version": "12.8.2",
    "test_type": "lab",
    "scores": {
      "performance": 88.0,
      "accessibility": 100,
      "best_practices": 75.0,
      "seo": 100
    },
    "metrics": {
      "first_contentful_paint": 1222.5240000000001,
      "largest_contentful_paint": 2148.5955,
      "cumulative_layout_shift": 0,
      "total_blocking_time": 437.5,
      "speed_index": 1860.937469958023,
      "interactive": 3311.1149
    },
    "throttling_config": {
      "method": "simulate",
      "device": "desktop"
    }
  },
  {
    "name": "Queen's University Belfast",
    "url": "https://www.qub.ac.uk",
    "device": "mobile",
    "timestamp": "2025-10-31T06:37:12.716770",
    "lighthouse_version": "12.8.2",
    "test_type": "lab",
    "scores": {
      "performance": 36.0,
      "accessibility": 95.0,
      "best_practices": 75.0,
      "seo": 85.0
    },
    "metrics": {
      "first_contentful_paint": 1754.632,
      "largest_contentful_paint": 11642.49,
      "cumulative_layout_shift": 0.11190761783216248,
      "total_blocking_time": 21210.391999999996,
      "speed_index": 5381.751251915111,
      "interactive": 41852.44125
    },
    "throttling_config": {
      "method": "simulate",
      "device": "mobile"
    }
  },
  {
    "name": "Queen's University Belfast",
    "url": "https://www.qub.ac.uk",
    "device": "desktop",
    "timestamp": "2025-10-31T06:37:15.279436",
    "lighthouse_version": "12.8.2",
    "test_type": "lab",
    "scores": {
      "performance": 63.0,
      "accessibility": 95.0,
      "best_practices": 75.0,
      "seo": 85.0
    },
    "metrics": {
      "first_contentful_paint": 1088.521,
      "largest_contentful_paint": 3248.8175,
      "cumulative_layout_shift": 0,
      "total_blocking_time": 4314.0284999999985,
      "speed_index": 1900.6612342327282,
      "interactive": 8686.606049999999
    },
    "throttling_config": {
      "method": "simulate",
      "device": "desktop"
    }
  },
  {
    "name": "Loughborough University",
    "url": "https://www.lboro.ac.uk",
    "device": "mobile",
    "timestamp": "2025-10-31T06:37:18.710607",
    "lighthouse_version": "12.8.2",
    "test_type": "lab",
    "scores": {
      "performance": 45.0,
      "accessibility": 100,
      "best_practices": 75.0,
      "seo": 100
    },
    "metrics": {
      "first_contentful_paint": 2719.248,
      "largest_contentful_paint": 7262.044165519713,
      "cumulative_layout_shift": 0.0168713668238293,
      "total_blocking_time": 1365.4999999999995,
      "speed_index": 4139.784189136196,
      "interactive": 7412.500132071685
    },
    "throttling_config": {
      "method": "simulate",
      "device": "mobile"
    }
  },
  {
    "name": "Loughborough University",
    "url": "https://www.lboro.ac.uk",
    "device": "desktop",
    "timestamp": "2025-10-31T06:37:19.832374",
    "lighthouse_version": "12.8.2",
    "test_type": "lab",
    "scores": {
      "performance": 100,
      "accessibility": 100,
      "best_practices": 75.0,
      "seo": 100
    },
    "metrics": {
      "first_contentful_paint": 382.515,
      "largest_contentful_paint": 1022.5176655197145,
      "cumulative_layout_shift": 0.0168713668238293,
      "total_blocking_time": 81,
      "speed_index": 1186.0055151141983,
      "interactive": 1563.0199320716856
    },
    "throttling_config": {
      "method": "simulate",
      "device": "desktop"
    }
  },
  {
    "name": "University of Leicester",
    "url": "https://www.le.ac.uk",
    "device": "mobile",
    "timestamp": "2025-10-31T06:37:40.927423",
    "lighthouse_version": "12.8.2",
    "test_type": "lab",
    "scores": {
      "performance": 31.0,
      "accessibility": 99.0,
      "best_practices": 96.0,
      "seo": 100
    },
    "metrics": {
      "first_contentful_paint": 3217.5629999999996,
      "largest_contentful_paint": 7573.502999999999,
      "cumulative_layout_shift": 0.1543134872417983,
      "total_blocking_time": 1940.5,
      "speed_index": 5902.559556847176,
      "interactive": 20265.3995
    },
    "throttling_config": {
      "method": "simulate",
      "device": "mobile"
    }
  },
  {
    "name": "University of Leicester",
    "url": "https://www.le.ac.uk",
    "device": "desktop",
    "timestamp": "2025-10-31T06:37:52.593029",
    "lighthouse_version": "12.8.2",
    "test_type": "lab",
    "scores": {
      "performance": 80.0,
      "accessibility": 99.0,
      "best_practices": 96.0,
      "seo": 100
    },
    "metrics": {
      "first_contentful_paint": 1333.7389999999998,
      "largest_contentful_paint": 2069.0009999999997,
      "cumulative_layout_shift": 0.1543134872417983,
      "total_blocking_time": 514.9999999999991,
      "speed_index": 2092.1074134628325,
      "interactive": 5190.676999999999
    },
    "throttling_config": {
      "method": "simulate",
      "device": "desktop"
    }
  },
  {
    "name": "University of Reading",
    "url": "https://www.reading.ac.uk",
    "device": "mobile",
    "timestamp": "2025-10-31T06:38:25.899954",
    "lighthouse_version": "12.8.2",
    "test_type": "lab",
    "scores": {
      "performance": 18.0,
      "accessibility": 95.0,
      "best_practices": 71.0,
      "seo": 83.0
    },
    "metrics": {
      "first_contentful_paint": 5309.9068,
      "largest_contentful_paint": 9502.358199999999,
      "cumulative_layout_shift": 0.17067038322587694,
      "total_blocking_time": 4962.5000000000055,
      "speed_index": 12809.485285988529,
      "interactive": 25098.672040000005
    },
    "throttling_config": {
      "method": "simulate",
      "device": "mobile"
    }
  },
  {
    "name": "City, University of London",
    "url": "https://www.city.ac.uk",
    "device": "mobile",
    "timestamp": "2025-10-31T06:38:26.408466",
    "lighthouse_version": "12.8.2",
    "test_type": "lab",
    "scores": {
      "performance": 41.0,
      "accessibility": 96.0,
      "best_practices": 96.0,
      "seo": 100
    },
    "metrics": {
      "first_contentful_paint": 3324.6495,
      "largest_contentful_paint": 6956.6435,
      "cumulative_layout_shift": 0.04381760035675253,
      "total_blocking_time": 1432.5,
      "speed_index": 4799.14528469853,
      "interactive": 10117.779750000002
    },
    "throttling_config": {
      "method": "simulate",
      "device": "mobile"
    }
  },
  {
    "name": "University of Reading",
    "url": "https://www.reading.ac.uk",
    "device": "desktop",
    "timestamp": "2025-10-31T06:38:26.599350",
    "lighthouse_version": "12.8.2",
    "test_type": "lab",
    "scores": {
      "performance": 56.00000000000001,
      "accessibility": 95.0,
      "best_practices": 71.0,
      "seo": 83.0
    },
    "metrics": {
      "first_contentful_paint": 1732.1522000000004,
      "largest_contentful_paint": 4040.398000000001,
      "cumulative_layout_shift": 0.17067038322587694,
      "total_blocking_time": 702.4999999999993,
      "speed_index": 5742.460314524233,
      "interactive": 4906.795499999999
    },
    "throttling_config": {
      "method": "simulate",
      "device": "desktop"
    }
  },
  {
    "name": "Swansea University",
    "url": "https://www.swansea.ac.uk",
    "device": "mobile",
    "timestamp": "2025-10-31T06:38:26.618950",
    "lighthouse_version": "12.8.2",
    "test_type": "lab",
    "scores": {
      "performance": 31.0,
      "accessibility": 100,
      "best_practices": 79.0,
      "seo": 100
    },
    "metrics": {
      "first_contentful_paint": 4098.505999999999,
      "largest_contentful_paint": 7609.369999999999,
      "cumulative_layout_shift": 0.00016392513830058953,
      "total_blocking_time": 11638.621500000008,
      "speed_index": 7186.017052608255,
      "interactive": 28457.854600000006
    },
    "throttling_config": {
      "method": "simulate",
      "device": "mobile"
    }
  },
  {
    "name": "City, University of London",
    "url": "https://www.city.ac.uk",
    "device": "desktop",
    "timestamp": "2025-10-31T06:38:28.434224",
    "lighthouse_version": "12.8.2",
    "test_type": "lab",
    "scores": {
      "performance": 86.0,
      "accessibility": 96.0,
      "best_practices": 96.0,
      "seo": 100
    },
    "metrics": {
      "first_contentful_paint": 2172.3305,
      "largest_contentful_paint": 3576.64325,
      "cumulative_layout_shift": 0,
      "total_blocking_time": 139,
      "speed_index": 2797.4521828023544,
      "interactive": 3634.4934750000007
    },
    "throttling_config": {
      "method": "simulate",
      "device": "desktop"
    }
  },
  {
    "name": "Brunel University London",
    "url": "https://www.brunel.ac.uk",
    "device": "mobile",
    "timestamp": "2025-10-31T06:38:39.655044",
    "lighthouse_version": "12.8.2",
    "test_type": "lab",
    "scores": {
      "performance": 28.999999999999996,
      "accessibility": 100,
      "best_practices": 79.0,
      "seo": 100
    },
    "metrics": {
      "first_contentful_paint": 4568.200999999999,
      "largest_contentful_paint": 13943.675,
      "cumulative_layout_shift": 0.0034955093168860148,
      "total_blocking_time": 9372.704000000003,
      "speed_index": 7286.463620651328,
      "interactive": 18163.133800000003
    },
    "throttling_config": {
      "method": "simulate",
      "device": "mobile"
    }
  },
  {
    "name": "Swansea University",
    "url": "https://www.swansea.ac.uk",
    "device": "desktop",
    "timestamp": "2025-10-31T06:38:45.022477",
    "lighthouse_version": "12.8.2",
    "test_type": "lab",
    "scores": {
      "performance": 74.0,
      "accessibility": 100,
      "best_practices": 79.0,
      "seo": 100
    },
    "metrics": {
      "first_contentful_paint": 1360.605,
      "largest_contentful_paint": 1710.2549999999999,
      "cumulative_layout_shift": 0.00016392513830058953,
      "total_blocking_time": 1397.0000000000011,
      "speed_index": 2557.3825208373455,
      "interactive": 5978.381500000002
    },
    "throttling_config": {
      "method": "simulate",
      "device": "desktop"
    }
  },
  {
    "name": "Brunel University London",
    "url": "https://www.brunel.ac.uk",
    "device": "desktop",
    "timestamp": "2025-10-31T06:38:47.287878",
    "lighthouse_version": "12.8.2",
    "test_type": "lab",
    "scores": {
      "performance": 66.0,
      "accessibility": 100,
      "best_practices": 75.0,
      "seo": 100
    },
    "metrics": {
      "first_contentful_paint": 1432.506,
      "largest_contentful_paint": 3295.0615000000007,
      "cumulative_layout_shift": 0.0034955093168860148,
      "total_blocking_time": 1597.5154999999993,
      "speed_index": 2312.118125237602,
      "interactive": 4170.7015
    },
    "throttling_config": {
      "method": "simulate",
      "device": "desktop"
    }
  },
  {
    "name": "Oxford Brookes University",
    "url": "https://www.brookes.ac.uk",
    "device": "mobile",
    "timestamp": "2025-10-31T06:39:06.508955",
    "lighthouse_version": "12.8.2",
    "test_type": "lab",
    "scores": {
      "performance": 38.0,
      "accessibility": 100,
      "best_practices": 75.0,
      "seo": 92.0
    },
    "metrics": {
      "first_contentful_paint": 2750.55368,
      "largest_contentful_paint": 9158.23921,
      "cumulative_layout_shift": 0.040824619983975616,
      "total_blocking_time": 3789.9511600000005,
      "speed_index": 4717.223669306242,
      "interactive": 12349.455514000001
    },
    "throttling_config": {
      "method": "simulate",
      "device": "mobile"
    }
  },
  {
    "name": "Oxford Brookes University",
    "url": "https://www.brookes.ac.uk",
    "device": "desktop",
    "timestamp": "2025-10-31T06:39:17.545008",
    "lighthouse_version": "12.8.2",
    "test_type": "lab",
    "scores": {
      "performance": 85.0,
      "accessibility": 100,
      "best_practices": 75.0,
      "seo": 92.0
    },
    "metrics": {
      "first_contentful_paint": 1440.3120000000001,
      "largest_contentful_paint": 4163.86,
      "cumulative_layout_shift": 0,
      "total_blocking_time": 113,
      "speed_index": 2687.5727890833323,
      "interactive": 4244.014800000001
    },
    "throttling_config": {
      "method": "simulate",
      "device": "desktop"
    }
  },
  {
    "name": "Aston University",
    "url": "https://www.aston.ac.uk",
    "device": "mobile",
    "timestamp": "2025-10-31T06:39:30.092196",
    "lighthouse_version": "12.8.2",
    "test_type": "lab",
    "scores": {
      "performance": 41.0,
      "accessibility": 92.0,
      "best_practices": 79.0,
      "seo": 92.0
    },
    "metrics": {
      "first_contentful_paint": 1154.0520000000001,
      "largest_contentful_paint": 15634.204,
      "cumulative_layout_shift": 0.0003047951614972156,
      "total_blocking_time": 15041.080000000002,
      "speed_index": 5193.915410899532,
      "interactive": 36326.05830000002
    },
    "throttling_config": {
      "method": "simulate",
      "device": "mobile"
    }
  },
  {
    "name": "Aston University",
    "url": "https://www.aston.ac.uk",
    "device": "desktop",
    "timestamp": "2025-10-31T06:39:30.193396",
    "lighthouse_version": "12.8.2",
    "test_type": "lab",
    "scores": {
      "performance": 55.00000000000001,
      "accessibility": 92.0,
      "best_practices": 79.0,
      "seo": 92.0
    },
    "metrics": {
      "first_contentful_paint": 394.45799999999997,
      "largest_contentful_paint": 4392.190500000001,
      "cumulative_layout_shift": 0,
      "total_blocking_time": 2995.2545,
      "speed_index": 2543.918349870398,
      "interactive": 7406.988950000001
    },
    "throttling_config": {
      "method": "simulate",
      "device": "desktop"
    }
  },
  {
    "name": "University of Kent",
    "url": "https://www.kent.ac.uk",
    "device": "desktop",
    "timestamp": "2025-10-31T06:39:30.804759",
    "lighthouse_version": "12.8.2",
    "test_type": "lab",
    "scores": {
      "performance": 68.0,
      "accessibility": 89.0,
      "best_practices": 61.0,
      "seo": 85.0
    },
    "metrics": {
      "first_contentful_paint": 848.0450000000001,
      "largest_contentful_paint": 1468.383,
      "cumulative_layout_shift": 0,
      "total_blocking_time": 4248.999999999999,
      "speed_index": 4271.769426587375,
      "interactive": 8218.895
    },
    "throttling_config": {
      "method": "simulate",
      "device": "desktop"
    }
  },
  {
    "name": "University of Kent",
    "url": "https://www.kent.ac.uk",
    "device": "mobile",
    "timestamp": "2025-10-31T06:39:31.160499",
    "lighthouse_version": "12.8.2",
    "test_type": "lab",
    "scores": {
      "performance": 51.0,
      "accessibility": 89.0,
      "best_practices": 61.0,
      "seo": 85.0
    },
    "metrics": {
      "first_contentful_paint": 1949.7689999999998,
      "largest_contentful_paint": 3395.0370000000003,
      "cumulative_layout_shift": 0.0018602481216661326,
      "total_blocking_time": 23701.927999999996,
      "speed_index": 10942.005119095253,
      "interactive": 30907.504199999996
    },
    "throttling_config": {
      "method": "simulate",
      "device": "mobile"
    }
  },
  {
    "name": "Birkbeck, University of London",
    "url": "https://www.bbk.ac.uk",
    "device": "desktop",
    "timestamp": "2025-10-31T06:39:49.465666",
    "lighthouse_version": "12.8.2",
    "test_type": "lab",
    "scores": {
      "performance": 78.0,
      "accessibility": 93.0,
      "best_practices": 100,
      "seo": 85.0
    },
    "metrics": {
      "first_contentful_paint": 559.7485,
      "largest_contentful_paint": 905.1155,
      "cumulative_layout_shift": 0.5980670265737513,
      "total_blocking_time": 14.5,
      "speed_index": 1154.9821705904274,
      "interactive": 1784.5314999999996
    },
    "throttling_config": {
      "method": "simulate",
      "device": "desktop"
    }
  },
  {
    "name": "Birkbeck, University of London",
    "url": "https://www.bbk.ac.uk",
    "device": "mobile",
    "timestamp": "2025-10-31T06:39:49.837504",
    "lighthouse_version": "12.8.2",
    "test_type": "lab",
    "scores": {
      "performance": 50.0,
      "accessibility": 93.0,
      "best_practices": 100,
      "seo": 85.0
    },
    "metrics": {
      "first_contentful_paint": 1801.875,
      "largest_contentful_paint": 3936.8560000000007,
      "cumulative_layout_shift": 0.6038500360122959,
      "total_blocking_time": 512.4999999999995,
      "speed_index": 3417.2164370303954,
      "interactive": 7591.0119
    },
    "throttling_config": {
      "method": "simulate",
      "device": "mobile"
    }
  },
  {
    "name": "Goldsmiths, University of London",
    "url": "https://www.gold.ac.uk",
    "device": "mobile",
    "timestamp": "2025-10-31T06:40:06.462038",
    "lighthouse_version": "12.8.2",
    "test_type": "lab",
    "scores": {
      "performance": 39.0,
      "accessibility": 100,
      "best_practices": 79.0,
      "seo": 100
    },
    "metrics": {
      "first_contentful_paint": 2697.2865,
      "largest_contentful_paint": 7640.885000000001,
      "cumulative_layout_shift": 0.00046296878318960086,
      "total_blocking_time": 2565.5,
      "speed_index": 5154.522247858488,
      "interactive": 16722.541900000004
    },
    "throttling_config": {
      "method": "simulate",
      "device": "mobile"
    }
  },
  {
    "name": "Goldsmiths, University of London",
    "url": "https://www.gold.ac.uk",
    "device": "desktop",
    "timestamp": "2025-10-31T06:40:08.024262",
    "lighthouse_version": "12.8.2",
    "test_type": "lab",
    "scores": {
      "performance": 89.0,
      "accessibility": 100,
      "best_practices": 79.0,
      "seo": 100
    },
    "metrics": {
      "first_contentful_paint": 1094.1605,
      "largest_contentful_paint": 1319.6684999999998,
      "cumulative_layout_shift": 0.00018231183895918874,
      "total_blocking_time": 460.24392000000034,
      "speed_index": 1744.6434324691627,
      "interactive": 3814.318888
    },
    "throttling_config": {
      "method": "simulate",
      "device": "desktop"
    }
  },
  {
    "name": "Aberystwyth University",
    "url": "https://www.aber.ac.uk",
    "device": "mobile",
    "timestamp": "2025-10-31T06:40:11.368901",
    "lighthouse_version": "12.8.2",
    "test_type": "lab",
    "scores": {
      "performance": 44.0,
      "accessibility": 100,
      "best_practices": 100,
      "seo": 83.0
    },
    "metrics": {
      "first_contentful_paint": 2934.615,
      "largest_contentful_paint": 7861.842999999999,
      "cumulative_layout_shift": 0.19927095990279464,
      "total_blocking_time": 574.3347499999995,
      "speed_index": 4490.690963853522,
      "interactive": 8777.032099999999
    },
    "throttling_config": {
      "method": "simulate",
      "device": "mobile"
    }
  },
  {
    "name": "Aberystwyth University",
    "url": "https://www.aber.ac.uk",
    "device": "desktop",
    "timestamp": "2025-10-31T06:40:12.217500",
    "lighthouse_version": "12.8.2",
    "test_type": "lab",
    "scores": {
      "performance": 75.0,
      "accessibility": 100,
      "best_practices": 100,
      "seo": 83.0
    },
    "metrics": {
      "first_contentful_paint": 1429.453,
      "largest_contentful_paint": 1809.5919999999996,
      "cumulative_layout_shift": 0.9141060188254158,
      "total_blocking_time": 38,
      "speed_index": 1891.0779153540848,
      "interactive": 2323.4810999999995
    },
    "throttling_config": {
      "method": "simulate",
      "device": "desktop"
    }
  },
  {
    "name": "Royal Holloway, University of London",
    "url": "https://www.rhul.ac.uk",
    "device": "mobile",
    "timestamp": "2025-10-31T06:40:29.982654",
    "lighthouse_version": "12.8.2",
    "test_type": "lab",
    "scores": {
      "performance": 31.0,
      "accessibility": 96.0,
      "best_practices": 75.0,
      "seo": 91.0
    },
    "metrics": {
      "first_contentful_paint": 4532.9839999999995,
      "largest_contentful_paint": 13792.4435,
      "cumulative_layout_shift": 0.03034575885574071,
      "total_blocking_time": 3514.499999999999,
      "speed_index": 6353.330264931109,
      "interactive": 18101.67575
    },
    "throttling_config": {
      "method": "simulate",
      "device": "mobile"
    }
  },
  {
    "name": "Robert Gordon University",
    "url": "https://www.rgu.ac.uk",
    "device": "mobile",
    "timestamp": "2025-10-31T06:40:31.791995",
    "lighthouse_version": "12.8.2",
    "test_type": "lab",
    "scores": {
      "performance": 56.99999999999999,
      "accessibility": 100,
      "best_practices": 96.0,
      "seo": 92.0
    },
    "metrics": {
      "first_contentful_paint": 5335.006899999998,
      "largest_contentful_paint": 15045.53715,
      "cumulative_layout_shift": 0.12443917122305378,
      "total_blocking_time": 47,
      "speed_index": 5335.006899999998,
      "interactive": 15053.046875
    },
    "throttling_config": {
      "method": "simulate",
      "device": "mobile"
    }
  },
  {
    "name": "Robert Gordon University",
    "url": "https://www.rgu.ac.uk",
    "device": "desktop",
    "timestamp": "2025-10-31T06:40:32.951060",
    "lighthouse_version": "12.8.2",
    "test_type": "lab",
    "scores": {
      "performance": 82.0,
      "accessibility": 100,
      "best_practices": 96.0,
      "seo": 92.0
    },
    "metrics": {
      "first_contentful_paint": 2093.0079999999994,
      "largest_contentful_paint": 3004.780683665712,
      "cumulative_layout_shift": 0.22101279504509194,
      "total_blocking_time": 0,
      "speed_index": 2215.907100814108,
      "interactive": 3010.88348907076
    },
    "throttling_config": {
      "method": "simulate",
      "device": "desktop"
    }
  },
  {
    "name": "Royal Holloway, University of London",
    "url": "https://www.rhul.ac.uk",
    "device": "desktop",
    "timestamp": "2025-10-31T06:40:40.390338",
    "lighthouse_version": "12.8.2",
    "test_type": "lab",
    "scores": {
      "performance": 76.0,
      "accessibility": 96.0,
      "best_practices": 75.0,
      "seo": 91.0
    },
    "metrics": {
      "first_contentful_paint": 1342.725,
      "largest_contentful_paint": 3581.474,
      "cumulative_layout_shift": 0.03034575885574071,
      "total_blocking_time": 532,
      "speed_index": 2151.181491974673,
      "interactive": 4265.039200000001
    },
    "throttling_config": {
      "method": "simulate",
      "device": "desktop"
    }
  },
  {
    "name": "Edinburgh Napier University",
    "url": "https://www.napier.ac.uk",
    "device": "mobile",
    "timestamp": "2025-10-31T06:40:59.943236",
    "lighthouse_version": "12.8.2",
    "test_type": "lab",
    "scores": {
      "performance": 36.0,
      "accessibility": 96.0,
      "best_practices": 100,
      "seo": 92.0
    },
    "metrics": {
      "first_contentful_paint": 4785.809000000001,
      "largest_contentful_paint": 13220.1915,
      "cumulative_layout_shift": 0.0015532115590791394,
      "total_blocking_time": 1228,
      "speed_index": 6290.270084773383,
      "interactive": 24013.54110000001
    },
    "throttling_config": {
      "method": "simulate",
      "device": "mobile"
    }
  },
  {
    "name": "Edinburgh Napier University",
    "url": "https://www.napier.ac.uk",
    "device": "desktop",
    "timestamp": "2025-10-31T06:41:01.709423",
    "lighthouse_version": "12.8.2",
    "test_type": "lab",
    "scores": {
      "performance": 90.0,
      "accessibility": 96.0,
      "best_practices": 100,
      "seo": 92.0
    },
    "metrics": {
      "first_contentful_paint": 1670.5890000000002,
      "largest_contentful_paint": 3338.0197499999995,
      "cumulative_layout_shift": 0.0015532115590791394,
      "total_blocking_time": 133.5,
      "speed_index": 2670.3095484167316,
      "interactive": 4711.9016
    },
    "throttling_config": {
      "method": "simulate",
      "device": "desktop"
    }
  },
  {
    "name": "Northumbria University",
    "url": "https://www.northumbria.ac.uk",
    "device": "mobile",
    "timestamp": "2025-10-31T06:41:14.609803",
    "lighthouse_version": "12.8.2",
    "test_type": "lab",
    "scores": {
      "performance": 33.0,
      "accessibility": 89.0,
      "best_practices": 75.0,
      "seo": 92.0
    },
    "metrics": {
      "first_contentful_paint": 3273.366,
      "largest_contentful_paint": 23872.001500000006,
      "cumulative_layout_shift": 0.029660270977361434,
      "total_blocking_time": 2638.500000000002,
      "speed_index": 7792.214342244806,
      "interactive": 27184.559000000005
    },
    "throttling_config": {
      "method": "simulate",
      "device": "mobile"
    }
  },
  {
    "name": "University of Essex",
    "url": "https://www.essex.ac.uk",
    "device": "mobile",
    "timestamp": "2025-10-31T06:41:15.286049",
    "lighthouse_version": "12.8.2",
    "test_type": "lab",
    "scores": {
      "performance": 31.0,
      "accessibility": 92.0,
      "best_practices": 54.0,
      "seo": 92.0
    },
    "metrics": {
      "first_contentful_paint": 2672.822,
      "largest_contentful_paint": 16336.645999999999,
      "cumulative_layout_shift": 0.07290400972053462,
      "total_blocking_time": 8610.499999999995,
      "speed_index": 11486.825801813538,
      "interactive": 33384.49605999999
    },
    "throttling_config": {
      "method": "simulate",
      "device": "mobile"
    }
  },
  {
    "name": "University of Essex",
    "url": "https://www.essex.ac.uk",
    "device": "desktop",
    "timestamp": "2025-10-31T06:41:16.866130",
    "lighthouse_version": "12.8.2",
    "test_type": "lab",
    "scores": {
      "performance": 65.0,
      "accessibility": 92.0,
      "best_practices": 54.0,
      "seo": 92.0
    },
    "metrics": {
      "first_contentful_paint": 1010.8063,
      "largest_contentful_paint": 3458.8177499999997,
      "cumulative_layout_shift": 0.07290400972053462,
      "total_blocking_time": 1295.1406000000002,
      "speed_index": 3433.4664623189406,
      "interactive": 6865.283464999999
    },
    "throttling_config": {
      "method": "simulate",
      "device": "desktop"
    }
  },
  {
    "name": "University of Bradford",
    "url": "https://www.bradford.ac.uk",
    "device": "mobile",
    "timestamp": "2025-10-31T06:41:20.849958",
    "lighthouse_version": "12.8.2",
    "test_type": "lab",
    "scores": {
      "performance": 78.0,
      "accessibility": 100,
      "best_practices": 100,
      "seo": 92.0
    },
    "metrics": {
      "first_contentful_paint": 2478.2815,
      "largest_contentful_paint": 3557.38062,
      "cumulative_layout_shift": 0.0006185259158378628,
      "total_blocking_time": 356.2660000000001,
      "speed_index": 3022.7247641001622,
      "interactive": 5663.433329
    },
    "throttling_config": {
      "method": "simulate",
      "device": "mobile"
    }
  },
  {
    "name": "University of Bradford",
    "url": "https://www.bradford.ac.uk",
    "device": "desktop",
    "timestamp": "2025-10-31T06:41:21.889700",
    "lighthouse_version": "12.8.2",
    "test_type": "lab",
    "scores": {
      "performance": 100,
      "accessibility": 100,
      "best_practices": 100,
      "seo": 92.0
    },
    "metrics": {
      "first_contentful_paint": 886.494,
      "largest_contentful_paint": 1120.9875000000002,
      "cumulative_layout_shift": 0.0006185259158378628,
      "total_blocking_time": 0,
      "speed_index": 1063.5486322718293,
      "interactive": 1120.9875000000002
    },
    "throttling_config": {
      "method": "simulate",
      "device": "desktop"
    }
  },
  {
    "name": "Northumbria University",
    "url": "https://www.northumbria.ac.uk",
    "device": "desktop",
    "timestamp": "2025-10-31T06:41:22.060436",
    "lighthouse_version": "12.8.2",
    "test_type": "lab",
    "scores": {
      "performance": 66.0,
      "accessibility": 89.0,
      "best_practices": 75.0,
      "seo": 92.0
    },
    "metrics": {
      "first_contentful_paint": 1277.9519999999998,
      "largest_contentful_paint": 4622.755999999998,
      "cumulative_layout_shift": 0.013904110799319436,
      "total_blocking_time": 668.4999999999986,
      "speed_index": 2784.9522381818533,
      "interactive": 5434.120099999999
    },
    "throttling_config": {
      "method": "simulate",
      "device": "desktop"
    }
  },
  {
    "name": "University of Stirling",
    "url": "https://www.stir.ac.uk",
    "device": "mobile",
    "timestamp": "2025-10-31T06:41:29.164598",
    "lighthouse_version": "12.8.2",
    "test_type": "lab",
    "scores": {
      "performance": 48.0,
      "accessibility": 96.0,
      "best_practices": 75.0,
      "seo": 100
    },
    "metrics": {
      "first_contentful_paint": 1667.777,
      "largest_contentful_paint": 5862.5869999999995,
      "cumulative_layout_shift": 0,
      "total_blocking_time": 2017.499999999999,
      "speed_index": 3691.1023948583575,
      "interactive": 14100.657550000004
    },
    "throttling_config": {
      "method": "simulate",
      "device": "mobile"
    }
  },
  {
    "name": "University of Stirling",
    "url": "https://www.stir.ac.uk",
    "device": "desktop",
    "timestamp": "2025-10-31T06:41:30.437777",
    "lighthouse_version": "12.8.2",
    "test_type": "lab",
    "scores": {
      "performance": 96.0,
      "accessibility": 96.0,
      "best_practices": 75.0,
      "seo": 100
    },
    "metrics": {
      "first_contentful_paint": 781.258,
      "largest_contentful_paint": 1402.8489999999997,
      "cumulative_layout_shift": 0,
      "total_blocking_time": 234.02599999999984,
      "speed_index": 1296.4341313997888,
      "interactive": 3353.9374
    },
    "throttling_config": {
      "method": "simulate",
      "device": "desktop"
    }
  }
]