{
  "name": "Cardiff University",
  "slug": "cardiff-university",
  "url": "https://www.cardiff.ac.uk",
  "last_updated": "2025-10-22T06:35:05.077868",
  "total_tests": 28,
  "results": [
    {
      "name": "Cardiff University",
      "url": "https://www.cardiff.ac.uk",
      "device": "mobile",
      "timestamp": "2025-10-09T21:09:08.415684",
      "lighthouse_version": "12.8.2",
      "test_type": "lab",
      "scores": {
        "performance": 34.0,
        "accessibility": 93.0,
        "best_practices": 100,
        "seo": 100
      },
      "metrics": {
        "first_contentful_paint": 2554.613,
        "largest_contentful_paint": 8705.564,
        "cumulative_layout_shift": 0.044779775820463955,
        "total_blocking_time": 12497.999999999996,
        "speed_index": 7559.454371018545,
        "interactive": 16992.406
      },
      "throttling_config": {
        "method": "simulate",
        "device": "mobile"
      }
    },
    {
      "name": "Cardiff University",
      "url": "https://www.cardiff.ac.uk",
      "device": "desktop",
      "timestamp": "2025-10-09T21:09:10.249418",
      "lighthouse_version": "12.8.2",
      "test_type": "lab",
      "scores": {
        "performance": 71.0,
        "accessibility": 93.0,
        "best_practices": 100,
        "seo": 100
      },
      "metrics": {
        "first_contentful_paint": 852.115,
        "largest_contentful_paint": 2081.7725,
        "cumulative_layout_shift": 0.044779775820463955,
        "total_blocking_time": 1952.09,
        "speed_index": 2169.944663202839,
        "interactive": 3900.705
      },
      "throttling_config": {
        "method": "simulate",
        "device": "desktop"
      }
    },
    {
      "name": "Cardiff University",
      "url": "https://www.cardiff.ac.uk",
      "device": "mobile",
      "timestamp": "2025-10-10T06:33:51.069548",
      "lighthouse_version": "12.8.2",
      "test_type": "lab",
      "scores": {
        "performance": 43.0,
        "accessibility": 93.0,
        "best_practices": 100,
        "seo": 100
      },
      "metrics": {
        "first_contentful_paint": 3001.437,
        "largest_contentful_paint": 6222.687,
        "cumulative_layout_shift": 0.043601360667293844,
        "total_blocking_time": 1772.5,
        "speed_index": 4102.085892875592,
        "interactive": 8388.449200000001
      },
      "throttling_config": {
        "method": "simulate",
        "device": "mobile"
      }
    },
    {
      "name": "Cardiff University",
      "url": "https://www.cardiff.ac.uk",
      "device": "desktop",
      "timestamp": "2025-10-10T06:33:52.132192",
      "lighthouse_version": "12.8.2",
      "test_type": "lab",
      "scores": {
        "performance": 97.0,
        "accessibility": 93.0,
        "best_practices": 100,
        "seo": 100
      },
      "metrics": {
        "first_contentful_paint": 1338.97525,
        "largest_contentful_paint": 2383.4130000000005,
        "cumulative_layout_shift": 0.005920987157909393,
        "total_blocking_time": 108.00000000000011,
        "speed_index": 2229.9434619265558,
        "interactive": 2391.8749500000004
      },
      "throttling_config": {
        "method": "simulate",
        "device": "desktop"
      }
    },
    {
      "name": "Cardiff University",
      "url": "https://www.cardiff.ac.uk",
      "device": "mobile",
      "timestamp": "2025-10-11T06:30:55.079405",
      "lighthouse_version": "12.8.2",
      "test_type": "lab",
      "scores": {
        "performance": 46.0,
        "accessibility": 93.0,
        "best_practices": 100,
        "seo": 100
      },
      "metrics": {
        "first_contentful_paint": 2289.247,
        "largest_contentful_paint": 6526.0885,
        "cumulative_layout_shift": 0.043601360667293844,
        "total_blocking_time": 1721.1849999999995,
        "speed_index": 3457.486698324904,
        "interactive": 9349.313750000001
      },
      "throttling_config": {
        "method": "simulate",
        "device": "mobile"
      }
    },
    {
      "name": "Cardiff University",
      "url": "https://www.cardiff.ac.uk",
      "device": "desktop",
      "timestamp": "2025-10-11T06:30:55.984410",
      "lighthouse_version": "12.8.2",
      "test_type": "lab",
      "scores": {
        "performance": 97.0,
        "accessibility": 93.0,
        "best_practices": 100,
        "seo": 100
      },
      "metrics": {
        "first_contentful_paint": 1220.6047499999997,
        "largest_contentful_paint": 2259.116,
        "cumulative_layout_shift": 0.044779775820463955,
        "total_blocking_time": 127,
        "speed_index": 1676.3152873940037,
        "interactive": 2270.96865
      },
      "throttling_config": {
        "method": "simulate",
        "device": "desktop"
      }
    },
    {
      "name": "Cardiff University",
      "url": "https://www.cardiff.ac.uk",
      "device": "mobile",
      "timestamp": "2025-10-12T06:30:16.768635",
      "lighthouse_version": "12.8.2",
      "test_type": "lab",
      "scores": {
        "performance": 53.0,
        "accessibility": 93.0,
        "best_practices": 100,
        "seo": 100
      },
      "metrics": {
        "first_contentful_paint": 2705.7219999999998,
        "largest_contentful_paint": 6253.8045,
        "cumulative_layout_shift": 0.044779775820463955,
        "total_blocking_time": 770.9999999999991,
        "speed_index": 3711.3625600952,
        "interactive": 10071.0536
      },
      "throttling_config": {
        "method": "simulate",
        "device": "mobile"
      }
    },
    {
      "name": "Cardiff University",
      "url": "https://www.cardiff.ac.uk",
      "device": "desktop",
      "timestamp": "2025-10-12T06:30:16.907817",
      "lighthouse_version": "12.8.2",
      "test_type": "lab",
      "scores": {
        "performance": 100,
        "accessibility": 93.0,
        "best_practices": 100,
        "seo": 100
      },
      "metrics": {
        "first_contentful_paint": 969.6719999999999,
        "largest_contentful_paint": 1502.6599999999999,
        "cumulative_layout_shift": 0.044779775820463955,
        "total_blocking_time": 30.5,
        "speed_index": 1187.1820476193725,
        "interactive": 1734.6079999999997
      },
      "throttling_config": {
        "method": "simulate",
        "device": "desktop"
      }
    },
    {
      "name": "Cardiff University",
      "url": "https://www.cardiff.ac.uk",
      "device": "mobile",
      "timestamp": "2025-10-13T06:35:26.339385",
      "lighthouse_version": "12.8.2",
      "test_type": "lab",
      "scores": {
        "performance": 46.0,
        "accessibility": 93.0,
        "best_practices": 100,
        "seo": 100
      },
      "metrics": {
        "first_contentful_paint": 2579.893,
        "largest_contentful_paint": 6370.993,
        "cumulative_layout_shift": 0.044779775820463955,
        "total_blocking_time": 1446.5,
        "speed_index": 3995.9099867303134,
        "interactive": 8465.8903
      },
      "throttling_config": {
        "method": "simulate",
        "device": "mobile"
      }
    },
    {
      "name": "Cardiff University",
      "url": "https://www.cardiff.ac.uk",
      "device": "desktop",
      "timestamp": "2025-10-13T06:36:15.481107",
      "lighthouse_version": "12.8.2",
      "test_type": "lab",
      "scores": {
        "performance": 70.0,
        "accessibility": 82.0,
        "best_practices": 96.0,
        "seo": 40.0
      },
      "metrics": {
        "first_contentful_paint": 317.58522,
        "largest_contentful_paint": 1125.06027,
        "cumulative_layout_shift": 0.0207310383355885,
        "total_blocking_time": 5646,
        "speed_index": 656.4894077521074,
        "interactive": 9474.07783
      },
      "throttling_config": {
        "method": "simulate",
        "device": "desktop"
      }
    },
    {
      "name": "Cardiff University",
      "url": "https://www.cardiff.ac.uk",
      "device": "mobile",
      "timestamp": "2025-10-14T06:33:31.271655",
      "lighthouse_version": "12.8.2",
      "test_type": "lab",
      "scores": {
        "performance": 45.0,
        "accessibility": 93.0,
        "best_practices": 100,
        "seo": 100
      },
      "metrics": {
        "first_contentful_paint": 3053.9590000000003,
        "largest_contentful_paint": 6330.598999999999,
        "cumulative_layout_shift": 0.044779775820463955,
        "total_blocking_time": 1368,
        "speed_index": 4183.999552716392,
        "interactive": 8470.153275
      },
      "throttling_config": {
        "method": "simulate",
        "device": "mobile"
      }
    },
    {
      "name": "Cardiff University",
      "url": "https://www.cardiff.ac.uk",
      "device": "desktop",
      "timestamp": "2025-10-14T06:33:31.564817",
      "lighthouse_version": "12.8.2",
      "test_type": "lab",
      "scores": {
        "performance": 96.0,
        "accessibility": 93.0,
        "best_practices": 100,
        "seo": 100
      },
      "metrics": {
        "first_contentful_paint": 840.343,
        "largest_contentful_paint": 1540.6215000000002,
        "cumulative_layout_shift": 0.006096806263013082,
        "total_blocking_time": 240.50000000000023,
        "speed_index": 1275.92203037099,
        "interactive": 1852.1771000000003
      },
      "throttling_config": {
        "method": "simulate",
        "device": "desktop"
      }
    },
    {
      "name": "Cardiff University",
      "url": "https://www.cardiff.ac.uk",
      "device": "desktop",
      "timestamp": "2025-10-15T06:34:12.231186",
      "lighthouse_version": "12.8.2",
      "test_type": "lab",
      "scores": {
        "performance": 91.0,
        "accessibility": 93.0,
        "best_practices": 100,
        "seo": 100
      },
      "metrics": {
        "first_contentful_paint": 1417.4395,
        "largest_contentful_paint": 2814.053,
        "cumulative_layout_shift": 0.005920987157909393,
        "total_blocking_time": 239.6460000000003,
        "speed_index": 2261.6329658333298,
        "interactive": 2822.9364
      },
      "throttling_config": {
        "method": "simulate",
        "device": "desktop"
      }
    },
    {
      "name": "Cardiff University",
      "url": "https://www.cardiff.ac.uk",
      "device": "mobile",
      "timestamp": "2025-10-15T06:34:13.005951",
      "lighthouse_version": "12.8.2",
      "test_type": "lab",
      "scores": {
        "performance": 43.0,
        "accessibility": 93.0,
        "best_practices": 100,
        "seo": 100
      },
      "metrics": {
        "first_contentful_paint": 2893.831,
        "largest_contentful_paint": 6178.942,
        "cumulative_layout_shift": 0.044779775820463955,
        "total_blocking_time": 2389.499999999999,
        "speed_index": 3460.897077949233,
        "interactive": 9419.64215
      },
      "throttling_config": {
        "method": "simulate",
        "device": "mobile"
      }
    },
    {
      "name": "Cardiff University",
      "url": "https://www.cardiff.ac.uk",
      "device": "mobile",
      "timestamp": "2025-10-16T06:33:47.095048",
      "lighthouse_version": "12.8.2",
      "test_type": "lab",
      "scores": {
        "performance": 45.0,
        "accessibility": 93.0,
        "best_practices": 100,
        "seo": 100
      },
      "metrics": {
        "first_contentful_paint": 2491.6999999999994,
        "largest_contentful_paint": 6445.975,
        "cumulative_layout_shift": 0.044779775820463955,
        "total_blocking_time": 1559,
        "speed_index": 4225.2549292693,
        "interactive": 10385.22155
      },
      "throttling_config": {
        "method": "simulate",
        "device": "mobile"
      }
    },
    {
      "name": "Cardiff University",
      "url": "https://www.cardiff.ac.uk",
      "device": "desktop",
      "timestamp": "2025-10-16T06:33:49.435027",
      "lighthouse_version": "12.8.2",
      "test_type": "lab",
      "scores": {
        "performance": 98.0,
        "accessibility": 93.0,
        "best_practices": 100,
        "seo": 100
      },
      "metrics": {
        "first_contentful_paint": 1288.7847500000003,
        "largest_contentful_paint": 2307.0674999999997,
        "cumulative_layout_shift": 0.044788027643476294,
        "total_blocking_time": 29,
        "speed_index": 1670.364226311832,
        "interactive": 2320.1324999999997
      },
      "throttling_config": {
        "method": "simulate",
        "device": "desktop"
      }
    },
    {
      "name": "Cardiff University",
      "url": "https://www.cardiff.ac.uk",
      "device": "mobile",
      "timestamp": "2025-10-17T06:33:18.791160",
      "lighthouse_version": "12.8.2",
      "test_type": "lab",
      "scores": {
        "performance": 46.0,
        "accessibility": 93.0,
        "best_practices": 100,
        "seo": 100
      },
      "metrics": {
        "first_contentful_paint": 2293.095,
        "largest_contentful_paint": 6202.9349999999995,
        "cumulative_layout_shift": 0.044779775820463955,
        "total_blocking_time": 2073.5,
        "speed_index": 3434.164187748471,
        "interactive": 10045.0612
      },
      "throttling_config": {
        "method": "simulate",
        "device": "mobile"
      }
    },
    {
      "name": "Cardiff University",
      "url": "https://www.cardiff.ac.uk",
      "device": "desktop",
      "timestamp": "2025-10-17T06:33:19.140256",
      "lighthouse_version": "12.8.2",
      "test_type": "lab",
      "scores": {
        "performance": 96.0,
        "accessibility": 93.0,
        "best_practices": 100,
        "seo": 100
      },
      "metrics": {
        "first_contentful_paint": 1312.4875,
        "largest_contentful_paint": 2314.4919999999997,
        "cumulative_layout_shift": 0.044788027643476294,
        "total_blocking_time": 162.5,
        "speed_index": 1681.5469608714639,
        "interactive": 2323.0026
      },
      "throttling_config": {
        "method": "simulate",
        "device": "desktop"
      }
    },
    {
      "name": "Cardiff University",
      "url": "https://www.cardiff.ac.uk",
      "device": "desktop",
      "timestamp": "2025-10-18T06:31:20.781795",
      "lighthouse_version": "12.8.2",
      "test_type": "lab",
      "scores": {
        "performance": 95.0,
        "accessibility": 93.0,
        "best_practices": 100,
        "seo": 100
      },
      "metrics": {
        "first_contentful_paint": 1178.1715000000002,
        "largest_contentful_paint": 2209.351,
        "cumulative_layout_shift": 0.005920987157909393,
        "total_blocking_time": 194.49999999999977,
        "speed_index": 1716.5052139323175,
        "interactive": 2223.6604
      },
      "throttling_config": {
        "method": "simulate",
        "device": "desktop"
      }
    },
    {
      "name": "Cardiff University",
      "url": "https://www.cardiff.ac.uk",
      "device": "mobile",
      "timestamp": "2025-10-18T06:31:21.001732",
      "lighthouse_version": "12.8.2",
      "test_type": "lab",
      "scores": {
        "performance": 45.0,
        "accessibility": 93.0,
        "best_practices": 100,
        "seo": 100
      },
      "metrics": {
        "first_contentful_paint": 2275.777,
        "largest_contentful_paint": 6092.741999999998,
        "cumulative_layout_shift": 0.006096806263013082,
        "total_blocking_time": 2463.7489999999993,
        "speed_index": 3890.907561874872,
        "interactive": 9185.0207
      },
      "throttling_config": {
        "method": "simulate",
        "device": "mobile"
      }
    },
    {
      "name": "Cardiff University",
      "url": "https://www.cardiff.ac.uk",
      "device": "desktop",
      "timestamp": "2025-10-19T06:32:29.888992",
      "lighthouse_version": "12.8.2",
      "test_type": "lab",
      "scores": {
        "performance": 89.0,
        "accessibility": 93.0,
        "best_practices": 100,
        "seo": 100
      },
      "metrics": {
        "first_contentful_paint": 1691.1792500000001,
        "largest_contentful_paint": 2632.6035,
        "cumulative_layout_shift": 0.00591170598470259,
        "total_blocking_time": 311.66925000000015,
        "speed_index": 2513.670037216561,
        "interactive": 2632.6035
      },
      "throttling_config": {
        "method": "simulate",
        "device": "desktop"
      }
    },
    {
      "name": "Cardiff University",
      "url": "https://www.cardiff.ac.uk",
      "device": "mobile",
      "timestamp": "2025-10-19T06:32:30.222644",
      "lighthouse_version": "12.8.2",
      "test_type": "lab",
      "scores": {
        "performance": 41.0,
        "accessibility": 93.0,
        "best_practices": 100,
        "seo": 100
      },
      "metrics": {
        "first_contentful_paint": 3101.5740000000005,
        "largest_contentful_paint": 6460.2119999999995,
        "cumulative_layout_shift": 0.044779775820463955,
        "total_blocking_time": 2970.2949999999996,
        "speed_index": 3594.448625145087,
        "interactive": 10648.750250000001
      },
      "throttling_config": {
        "method": "simulate",
        "device": "mobile"
      }
    },
    {
      "name": "Cardiff University",
      "url": "https://www.cardiff.ac.uk",
      "device": "mobile",
      "timestamp": "2025-10-20T06:35:22.982004",
      "lighthouse_version": "12.8.2",
      "test_type": "lab",
      "scores": {
        "performance": 41.0,
        "accessibility": 93.0,
        "best_practices": 100,
        "seo": 100
      },
      "metrics": {
        "first_contentful_paint": 2412.5295,
        "largest_contentful_paint": 6751.0695,
        "cumulative_layout_shift": 0.07999729147414802,
        "total_blocking_time": 2819.000000000001,
        "speed_index": 4252.151274634067,
        "interactive": 10245.3166
      },
      "throttling_config": {
        "method": "simulate",
        "device": "mobile"
      }
    },
    {
      "name": "Cardiff University",
      "url": "https://www.cardiff.ac.uk",
      "device": "desktop",
      "timestamp": "2025-10-20T06:35:24.032324",
      "lighthouse_version": "12.8.2",
      "test_type": "lab",
      "scores": {
        "performance": 85.0,
        "accessibility": 93.0,
        "best_practices": 100,
        "seo": 100
      },
      "metrics": {
        "first_contentful_paint": 856.0709999999999,
        "largest_contentful_paint": 1597.882,
        "cumulative_layout_shift": 0.046469248787359176,
        "total_blocking_time": 567.5000000000005,
        "speed_index": 1247.4821666105356,
        "interactive": 2210.055700000001
      },
      "throttling_config": {
        "method": "simulate",
        "device": "desktop"
      }
    },
    {
      "name": "Cardiff University",
      "url": "https://www.cardiff.ac.uk",
      "device": "mobile",
      "timestamp": "2025-10-21T06:34:11.061015",
      "lighthouse_version": "12.8.2",
      "test_type": "lab",
      "scores": {
        "performance": 41.0,
        "accessibility": 93.0,
        "best_practices": 100,
        "seo": 100
      },
      "metrics": {
        "first_contentful_paint": 2911.7140000000004,
        "largest_contentful_paint": 6838.407999999999,
        "cumulative_layout_shift": 0.044779775820463955,
        "total_blocking_time": 2877.844,
        "speed_index": 3762.0065280421795,
        "interactive": 10328.8891
      },
      "throttling_config": {
        "method": "simulate",
        "device": "mobile"
      }
    },
    {
      "name": "Cardiff University",
      "url": "https://www.cardiff.ac.uk",
      "device": "desktop",
      "timestamp": "2025-10-21T06:34:12.618306",
      "lighthouse_version": "12.8.2",
      "test_type": "lab",
      "scores": {
        "performance": 95.0,
        "accessibility": 93.0,
        "best_practices": 100,
        "seo": 100
      },
      "metrics": {
        "first_contentful_paint": 1326.8379999999997,
        "largest_contentful_paint": 2623.729,
        "cumulative_layout_shift": 0.005920987157909393,
        "total_blocking_time": 142.5000000000001,
        "speed_index": 2196.539133879489,
        "interactive": 2632.2194
      },
      "throttling_config": {
        "method": "simulate",
        "device": "desktop"
      }
    },
    {
      "name": "Cardiff University",
      "url": "https://www.cardiff.ac.uk",
      "device": "mobile",
      "timestamp": "2025-10-22T06:35:04.078189",
      "lighthouse_version": "12.8.2",
      "test_type": "lab",
      "scores": {
        "performance": 45.0,
        "accessibility": 93.0,
        "best_practices": 100,
        "seo": 100
      },
      "metrics": {
        "first_contentful_paint": 2945.9429999999998,
        "largest_contentful_paint": 6094.273000000001,
        "cumulative_layout_shift": 0.044779775820463955,
        "total_blocking_time": 1481,
        "speed_index": 4027.1399924280595,
        "interactive": 9855.73775
      },
      "throttling_config": {
        "method": "simulate",
        "device": "mobile"
      }
    },
    {
      "name": "Cardiff University",
      "url": "https://www.cardiff.ac.uk",
      "device": "desktop",
      "timestamp": "2025-10-22T06:35:05.077868",
      "lighthouse_version": "12.8.2",
      "test_type": "lab",
      "scores": {
        "performance": 91.0,
        "accessibility": 93.0,
        "best_practices": 100,
        "seo": 100
      },
      "metrics": {
        "first_contentful_paint": 820.209,
        "largest_contentful_paint": 2290.9154999999996,
        "cumulative_layout_shift": 0.044788027643476294,
        "total_blocking_time": 330,
        "speed_index": 1374.9365567726118,
        "interactive": 2300.2116499999997
      },
      "throttling_config": {
        "method": "simulate",
        "device": "desktop"
      }
    }
  ]
}